src/__init__.py
src/albums.json
src/main.py
discover_daily-0.1.0.dist-info/LICENSE
discover_daily-0.1.0.dist-info/WHEEL
discover_daily-0.1.0.dist-info/entry_points.txt
discover_daily-0.1.0.dist-info/METADATA
discover_daily-0.1.0.dist-info/RECORD
